[{"place": 1, "skier": "Anja P\u00e4rson", "nation": "Sweden", "id": 44, "previous_elo": 1585.182461103082, "new_elo": 1605.1668943214509, "change": 19.98443321836885}, {"place": 2, "skier": "Michaela Dorfmeister", "nation": "Austria", "id": 809, "previous_elo": 1617.6783129753323, "new_elo": 1633.9376274406552, "change": 16.25931446532286}, {"place": 3, "skier": "Maria Jose Rienda Contreras", "nation": "Spain", "id": 108, "previous_elo": 1374.575359152548, "new_elo": 1412.6025409247677, "change": 38.02718177221982}, {"place": 4, "skier": "Maria H\u00f6fl-Riesch", "nation": "Germany", "id": 8, "previous_elo": 1468.576270425175, "new_elo": 1495.5655471711875, "change": 26.989276746012592}, {"place": 5, "skier": "Anna Ottoson", "nation": "Sweden", "id": 766, "previous_elo": 1399.1241118949924, "new_elo": 1432.110887579629, "change": 32.98677568463654}, {"place": 6, "skier": "Allison Forsyth", "nation": "Canada", "id": 832, "previous_elo": 1381.8852414516855, "new_elo": 1415.5015157895753, "change": 33.61627433788976}, {"place": 7, "skier": "Tanja Poutiainen", "nation": "Finland", "id": 21, "previous_elo": 1592.4190179275563, "new_elo": 1604.5677014690118, "change": 12.148683541455512}, {"place": 8, "skier": "Elisabeth G\u00f6rgl", "nation": "Austria", "id": 4, "previous_elo": 1466.4749434855871, "new_elo": 1488.8371238761342, "change": 22.36218039054711}, {"place": 9, "skier": "Andrine Flemmen", "nation": "Norway", "id": 835, "previous_elo": 1362.6195087700692, "new_elo": 1394.670508865796, "change": 32.05100009572675}, {"place": 10, "skier": "Alexandra Meissnitzer", "nation": "Austria", "id": 732, "previous_elo": 1587.18564446526, "new_elo": 1596.1231535621723, "change": 8.937509096912208}, {"place": 11, "skier": "Renate Goetschl", "nation": "Austria", "id": 356, "previous_elo": 1610.8570727151491, "new_elo": 1616.740982016454, "change": 5.883909301304811}, {"place": 12, "skier": "Silvia Berger", "nation": "Austria", "id": 657, "previous_elo": 1468.4041884784551, "new_elo": 1485.7345332740715, "change": 17.330344795616384}, {"place": 13, "skier": "Fraenzi Aufdenblatten", "nation": "Switzerland", "id": 23, "previous_elo": 1406.501581107507, "new_elo": 1429.0289546044053, "change": 22.527373496898235}, {"place": 14, "skier": "Stina Hofgaard Nilsen", "nation": "Norway", "id": 975, "previous_elo": 1388.8704856216227, "new_elo": 1412.0641605849682, "change": 23.19367496334553}, {"place": 15, "skier": "Brigitte Obermoser", "nation": "Austria", "id": 780, "previous_elo": 1456.8227787376502, "new_elo": 1471.6943123201422, "change": 14.87153358249202}, {"place": 16, "skier": "Chemmy Alcott", "nation": "Great Britain", "id": 134, "previous_elo": 1308.7212112549698, "new_elo": 1338.0434841579968, "change": 29.322272903026942}, {"place": 17, "skier": "Marlies Oester", "nation": "Switzerland", "id": 833, "previous_elo": 1419.502610882145, "new_elo": 1435.8193181279603, "change": 16.316707245815223}, {"place": 18, "skier": "Kirsten Clark", "nation": "USA", "id": 775, "previous_elo": 1549.2487760376032, "new_elo": 1551.6955627681912, "change": 2.4467867305879736}, {"place": 19, "skier": "Libby Ludlow", "nation": "USA", "id": 744, "previous_elo": 1282.3221736919147, "new_elo": 1310.760722944623, "change": 28.4385492527083}, {"place": 20, "skier": "Denise Karbon", "nation": "Italy", "id": 65, "previous_elo": 1438.7684102986557, "new_elo": 1449.445517166623, "change": 10.677106867967268}, {"place": 21, "skier": "Sarah Schleper", "nation": "USA", "id": 132, "previous_elo": 1541.562345282892, "new_elo": 1541.0590191708102, "change": -0.5033261120818224}, {"place": 22, "skier": "Carole Montillet-Carles", "nation": "France", "id": 810, "previous_elo": 1626.565534930102, "new_elo": 1617.983798601931, "change": -8.581736328171019}, {"place": 23, "skier": "Hilde Gerg", "nation": "Germany", "id": 905, "previous_elo": 1624.8685560262618, "new_elo": 1615.200268083532, "change": -9.668287942729876}, {"place": 24, "skier": "Tina Maze", "nation": "Slovenia", "id": 16, "previous_elo": 1392.926307434862, "new_elo": 1403.592068986541, "change": 10.665761551678997}, {"place": 25, "skier": "Brigitte Acton", "nation": "Canada", "id": 275, "previous_elo": 1292.6371886051177, "new_elo": 1312.7537488560706, "change": 20.116560250952944}, {"place": 26, "skier": "Magdalena Planatscher", "nation": "Italy", "id": 904, "previous_elo": 1298.5947179782206, "new_elo": 1316.882059257303, "change": 18.287341279082284}, {"place": 27, "skier": "Caroline Lalive", "nation": "USA", "id": 666, "previous_elo": 1434.5594906369708, "new_elo": 1437.2065843720986, "change": 2.6470937351277826}, {"place": 28, "skier": "Nicole Hosp", "nation": "Austria", "id": 32, "previous_elo": 1561.3889400311712, "new_elo": 1550.6911457908066, "change": -10.697794240364601}, {"place": 29, "skier": "Sonja Nef", "nation": "Switzerland", "id": 834, "previous_elo": 1583.6077256394285, "new_elo": 1569.8527802090418, "change": -13.75494543038667}, {"place": 30, "skier": "Lilian Kummer", "nation": "Switzerland", "id": 976, "previous_elo": 1354.277076135964, "new_elo": 1361.8218733254596, "change": 7.544797189495512}, {"place": 31, "skier": "Martina Lechner", "nation": "Austria", "id": 926, "previous_elo": 1279.3154764453584, "new_elo": 1293.548034275267, "change": 14.232557829908501}, {"place": 32, "skier": "Ingrid Jacquemod", "nation": "France", "id": 107, "previous_elo": 1410.2284748075433, "new_elo": 1409.380355086149, "change": -0.8481197213943688}, {"place": 33, "skier": "Eva Kurfuerstova", "nation": "Czechia", "id": 141, "previous_elo": 1219.765423377121, "new_elo": 1237.4380007815982, "change": 17.67257740447735}, {"place": 34, "skier": "Nika Fleiss", "nation": "Croatia", "id": 278, "previous_elo": 1328.803721733639, "new_elo": 1334.2306356925371, "change": 5.42691395889824}, {"place": 35, "skier": "Jessica Walter", "nation": "Liechtenstein", "id": 785, "previous_elo": 1254.5367846207605, "new_elo": 1266.4307145528428, "change": 11.893929932082301}, {"place": 36, "skier": "Ana Kobal", "nation": "Slovenia", "id": 191, "previous_elo": 1238.87896345194, "new_elo": 1251.099695558065, "change": 12.220732106124842}, {"place": 37, "skier": "Karoline Trojer", "nation": "Italy", "id": 668, "previous_elo": 1300.0, "new_elo": 1304.8359421347764, "change": 4.83594213477636}, {"place": 38, "skier": "Julie Duvillard", "nation": "France", "id": 843, "previous_elo": 1242.5899124785165, "new_elo": 1252.0307936787458, "change": 9.440881200229342}, {"place": 39, "skier": "Dagmara Krzyzynska", "nation": "Poland", "id": 798, "previous_elo": 1256.5183505398118, "new_elo": 1263.377231223314, "change": 6.858880683502321}, {"place": 40, "skier": "Ana Jelusic", "nation": "Croatia", "id": 129, "previous_elo": 1256.0277974925514, "new_elo": 1261.7259625788602, "change": 5.698165086308791}, {"place": 41, "skier": "Gail Kelly", "nation": "Canada", "id": 736, "previous_elo": 1261.4389923142828, "new_elo": 1265.3874306801245, "change": 3.948438365841639}, {"place": 42, "skier": "Sophie Fjellvang-Soelling", "nation": "Denmark", "id": 614, "previous_elo": 1283.2500889888192, "new_elo": 1283.7742480609088, "change": 0.5241590720895601}, {"place": 43, "skier": "Jelena Lolovic", "nation": "Serbia", "id": 267, "previous_elo": 1255.185552086878, "new_elo": 1257.3388684933068, "change": 2.1533164064287575}, {"place": 44, "skier": "Andreja Rataj", "nation": "Slovenia", "id": 932, "previous_elo": 1300.0, "new_elo": 1296.3692754681097, "change": -3.630724531890337}, {"place": 45, "skier": "Olesja Alieva", "nation": "Russia", "id": 811, "previous_elo": 1210.3863547367362, "new_elo": 1214.4165350735932, "change": 4.030180336857029}, {"place": 46, "skier": "Noora Haterma", "nation": "Finland", "id": 836, "previous_elo": 1300.0, "new_elo": 1293.9502278490622, "change": -6.04977215093777}, {"place": 47, "skier": "Kumiko Kashiwagi", "nation": "Japan", "id": 851, "previous_elo": 1264.4778165142034, "new_elo": 1260.8640375220566, "change": -3.613778992146763}, {"place": 48, "skier": "Lana Grandovec", "nation": "Slovenia", "id": 862, "previous_elo": 1300.0, "new_elo": 1291.5311802300146, "change": -8.46881976998543}, {"place": 49, "skier": "Tanja Schneider", "nation": "Austria", "id": 982, "previous_elo": 1348.2852212731852, "new_elo": 1333.490508422669, "change": -14.794712850516134}, {"place": 50, "skier": "Therese Borssen", "nation": "Sweden", "id": 121, "previous_elo": 1323.4736630491425, "new_elo": 1310.1142173303772, "change": -13.3594457187653}, {"place": 51, "skier": "Britt Janyk", "nation": "Canada", "id": 106, "previous_elo": 1315.7716732157794, "new_elo": 1302.0178142197797, "change": -13.753858995999735}, {"place": 52, "skier": "Julia Mancuso", "nation": "USA", "id": 6, "previous_elo": 1297.7532454110633, "new_elo": 1284.6806906799738, "change": -13.07255473108944}, {"place": 53, "skier": "Nicole Gius", "nation": "Italy", "id": 68, "previous_elo": 1403.1849417877395, "new_elo": 1377.683122738168, "change": -25.501819049571395}, {"place": 54, "skier": "Barbara Kleon", "nation": "Italy", "id": 903, "previous_elo": 1312.2622500128157, "new_elo": 1295.2499855665303, "change": -17.01226444628537}, {"place": 55, "skier": "Line Viken", "nation": "Norway", "id": 771, "previous_elo": 1313.7410040550144, "new_elo": 1295.3633412969518, "change": -18.37766275806257}, {"place": 56, "skier": "Manuela Moelgg", "nation": "Italy", "id": 67, "previous_elo": 1315.6296532622582, "new_elo": 1295.8431710647585, "change": -19.78648219749971}, {"place": 57, "skier": "Kristina Koznick", "nation": "USA", "id": 830, "previous_elo": 1512.5053649423162, "new_elo": 1471.1178474900169, "change": -41.387517452299335}, {"place": 58, "skier": "Emmanuelle Colomban", "nation": "France", "id": 860, "previous_elo": 1302.5273551937048, "new_elo": 1281.6991525448464, "change": -20.82820264885845}, {"place": 59, "skier": "Sarka Strachova", "nation": "Czechia", "id": 75, "previous_elo": 1340.8189210187948, "new_elo": 1314.727156510256, "change": -26.091764508538745}, {"place": 60, "skier": "Annemarie Gerg", "nation": "Germany", "id": 765, "previous_elo": 1358.7854288141514, "new_elo": 1329.5615560022893, "change": -29.223872811862066}, {"place": 61, "skier": "Mateja Robnik", "nation": "Slovenia", "id": 233, "previous_elo": 1300.0, "new_elo": 1275.807370706205, "change": -24.192629293795108}, {"place": 62, "skier": "Ana Drev", "nation": "Slovenia", "id": 64, "previous_elo": 1238.0701508137672, "new_elo": 1218.921618880806, "change": -19.148531932961305}, {"place": 63, "skier": "Audrey Peltier", "nation": "France", "id": 758, "previous_elo": 1291.1358504044572, "new_elo": 1265.4461528968584, "change": -25.689697507598794}, {"place": 64, "skier": "Laurence Lazier", "nation": "France", "id": 906, "previous_elo": 1288.9032698055785, "new_elo": 1262.2351006211052, "change": -26.6681691844733}, {"place": 65, "skier": "Maria Pietilae-Holmner", "nation": "Sweden", "id": 12, "previous_elo": 1275.752083186953, "new_elo": 1249.224902243175, "change": -26.52718094377815}, {"place": 66, "skier": "Marlies Schild", "nation": "Austria", "id": 13, "previous_elo": 1484.9773877352045, "new_elo": 1435.3489419559255, "change": -49.62844577927899}, {"place": 67, "skier": "Angelika Gruener", "nation": "Italy", "id": 673, "previous_elo": 1300.0, "new_elo": 1268.550227849062, "change": -31.449772150938088}, {"place": 68, "skier": "Nadia Styger", "nation": "Switzerland", "id": 265, "previous_elo": 1466.9522830838814, "new_elo": 1416.6950562534223, "change": -50.2572268304591}]