[{"place": 1, "skier": "Marlies Schild", "nation": "Austria", "id": 13, "previous_elo": 1566.4537534450096, "new_elo": 1578.1826582171193, "change": 11.728904772109672}, {"place": 2, "skier": "Maria H\u00f6fl-Riesch", "nation": "Germany", "id": 8, "previous_elo": 1682.6767843189143, "new_elo": 1688.6777443773406, "change": 6.000960058426244}, {"place": 3, "skier": "Manuela Moelgg", "nation": "Italy", "id": 67, "previous_elo": 1555.5782398744605, "new_elo": 1565.4897314145733, "change": 9.91149154011282}, {"place": 4, "skier": "Tanja Poutiainen", "nation": "Finland", "id": 21, "previous_elo": 1668.4319986974576, "new_elo": 1672.6010555936289, "change": 4.1690568961712415}, {"place": 5, "skier": "Maria Pietilae-Holmner", "nation": "Sweden", "id": 12, "previous_elo": 1560.314583454346, "new_elo": 1567.6918321094345, "change": 7.377248655088579}, {"place": 6, "skier": "Nastasia Noens", "nation": "France", "id": 122, "previous_elo": 1374.432040465696, "new_elo": 1390.484550945681, "change": 16.052510479984903}, {"place": 7, "skier": "Katrin Zettel", "nation": "Austria", "id": 18, "previous_elo": 1627.9344665833564, "new_elo": 1630.122490406299, "change": 2.1880238229425686}, {"place": 8, "skier": "Sarah Schleper", "nation": "USA", "id": 132, "previous_elo": 1322.1699428216743, "new_elo": 1338.894204139512, "change": 16.724261317837772}, {"place": 9, "skier": "Veronika Velez-Zuzulova", "nation": "Slovakia", "id": 71, "previous_elo": 1383.8489916085298, "new_elo": 1395.8897144753196, "change": 12.040722866789793}, {"place": 10, "skier": "Sandrine Aubert", "nation": "France", "id": 125, "previous_elo": 1443.0677365982733, "new_elo": 1450.6215882105748, "change": 7.553851612301514}, {"place": 11, "skier": "Ana Jelusic", "nation": "Croatia", "id": 129, "previous_elo": 1378.808229053776, "new_elo": 1388.8210538633723, "change": 10.012824809596395}, {"place": 12, "skier": "Therese Borssen", "nation": "Sweden", "id": 121, "previous_elo": 1467.864432890732, "new_elo": 1471.7559705859676, "change": 3.8915376952356837}, {"place": 13, "skier": "Tina Maze", "nation": "Slovenia", "id": 16, "previous_elo": 1599.8658286907755, "new_elo": 1596.2423473955785, "change": -3.6234812951970525}, {"place": 14, "skier": "Denise Feierabend", "nation": "Switzerland", "id": 117, "previous_elo": 1262.2876531234226, "new_elo": 1275.39821526418, "change": 13.110562140757338}, {"place": 15, "skier": "Anne-Sophie Barthet", "nation": "France", "id": 58, "previous_elo": 1238.7354737682874, "new_elo": 1251.9442309990677, "change": 13.208757230780293}, {"place": 16, "skier": "Katharina Duerr", "nation": "Germany", "id": 85, "previous_elo": 1358.8357372068322, "new_elo": 1364.202255760361, "change": 5.366518553528749}, {"place": 17, "skier": "Nina Perner", "nation": "Germany", "id": 124, "previous_elo": 1260.5419776218655, "new_elo": 1270.2732608508277, "change": 9.731283228962184}, {"place": 18, "skier": "Marina Nigg", "nation": "Liechtenstein", "id": 83, "previous_elo": 1290.641068793233, "new_elo": 1297.5618409062963, "change": 6.920772113063322}, {"place": 19, "skier": "Sarka Strachova", "nation": "Czechia", "id": 75, "previous_elo": 1447.5947744712985, "new_elo": 1444.479113239482, "change": -3.115661231816375}, {"place": 20, "skier": "Sanni Leinonen", "nation": "Finland", "id": 219, "previous_elo": 1337.082105774422, "new_elo": 1339.0619203072922, "change": 1.9798145328702503}, {"place": 21, "skier": "Veronika Staber", "nation": "Germany", "id": 158, "previous_elo": 1227.649721344356, "new_elo": 1234.4880139210438, "change": 6.838292576687763}, {"place": 22, "skier": "Emelie Wikstroem", "nation": "Sweden", "id": 87, "previous_elo": 1313.1951372067351, "new_elo": 1314.2177210604348, "change": 1.0225838536996434}, {"place": 23, "skier": "Nicole Hosp", "nation": "Austria", "id": 32, "previous_elo": 1494.7508032037626, "new_elo": 1484.4906546411069, "change": -10.260148562655786}, {"place": 24, "skier": "Barbara Wirth", "nation": "Germany", "id": 59, "previous_elo": 1270.3544832604482, "new_elo": 1271.4473773934037, "change": 1.0928941329555073}, {"place": 25, "skier": "Sofija Novoselic", "nation": "Croatia", "id": 139, "previous_elo": 1244.2615153509626, "new_elo": 1245.6001755490431, "change": 1.3386601980805608}, {"place": 26, "skier": "Sabrina Fanchini", "nation": "Italy", "id": 135, "previous_elo": 1306.675944161654, "new_elo": 1303.435025415008, "change": -3.240918746645775}, {"place": 27, "skier": "Marion Bertrand", "nation": "France", "id": 211, "previous_elo": 1280.3750224053306, "new_elo": 1277.443964027771, "change": -2.931058377559566}, {"place": 28, "skier": "Frida Hansdotter", "nation": "Sweden", "id": 73, "previous_elo": 1391.011248735373, "new_elo": 1380.6436599497306, "change": -10.36758878564251}, {"place": 29, "skier": "Susanne Riesch", "nation": "Germany", "id": 128, "previous_elo": 1406.173083235069, "new_elo": 1393.7871180686486, "change": -12.38596516642042}, {"place": 30, "skier": "Christina Ackermann", "nation": "Germany", "id": 77, "previous_elo": 1454.4253938085628, "new_elo": 1438.2001359555377, "change": -16.22525785302514}, {"place": 31, "skier": "Tea Palic", "nation": "Croatia", "id": 327, "previous_elo": 1286.020316041642, "new_elo": 1278.1453061059287, "change": -7.875009935713251}, {"place": 32, "skier": "Macarena Simari Birkner", "nation": "Argentina", "id": 55, "previous_elo": 1192.9119357089776, "new_elo": 1188.7524994332186, "change": -4.159436275758935}, {"place": 33, "skier": "Maria Belen Simari Birkner", "nation": "Argentina", "id": 56, "previous_elo": 1137.6916069122856, "new_elo": 1134.8912628633182, "change": -2.8003440489674176}, {"place": 34, "skier": "Marusa Ferk", "nation": "Slovenia", "id": 47, "previous_elo": 1347.4495570338067, "new_elo": 1332.6260062958029, "change": -14.82355073800386}, {"place": 35, "skier": "Katja Jazbec", "nation": "Slovenia", "id": 317, "previous_elo": 1257.8649838534943, "new_elo": 1246.8985482696787, "change": -10.96643558381561}, {"place": 36, "skier": "Hailey Duke", "nation": "USA", "id": 276, "previous_elo": 1232.2935135756825, "new_elo": 1221.5229173722682, "change": -10.770596203414243}, {"place": 37, "skier": "Taina Barioz", "nation": "France", "id": 57, "previous_elo": 1381.945692578444, "new_elo": 1361.674020366862, "change": -20.2716722115822}, {"place": 38, "skier": "Vanessa Schaedler", "nation": "Liechtenstein", "id": 325, "previous_elo": 1300.0, "new_elo": 1283.2397049979509, "change": -16.760295002049133}, {"place": 39, "skier": "Resi Stiegler", "nation": "USA", "id": 136, "previous_elo": 1295.8209554109108, "new_elo": 1278.1368423411952, "change": -17.684113069715522}]