[{"place": 1, "skier": "Lindsey Vonn", "nation": "USA", "id": 2, "previous_elo": 1694.091289692634, "new_elo": 1703.0383208970895, "change": 8.94703120445547}, {"place": 2, "skier": "Anja P\u00e4rson", "nation": "Sweden", "id": 44, "previous_elo": 1520.808568387649, "new_elo": 1538.0180060613618, "change": 17.209437673712728}, {"place": 3, "skier": "Anna Veith", "nation": "Austria", "id": 5, "previous_elo": 1476.146542721101, "new_elo": 1495.2492974724184, "change": 19.102754751317434}, {"place": 4, "skier": "Julia Mancuso", "nation": "USA", "id": 6, "previous_elo": 1470.4031129500186, "new_elo": 1488.7546449882288, "change": 18.35153203821028}, {"place": 5, "skier": "Lara Gut-Behrami", "nation": "Switzerland", "id": 10, "previous_elo": 1497.4559380212074, "new_elo": 1512.7612241810243, "change": 15.305286159816887}, {"place": 6, "skier": "Fabienne Suter", "nation": "Switzerland", "id": 11, "previous_elo": 1517.640840277547, "new_elo": 1529.8490941652694, "change": 12.208253887722321}, {"place": 6, "skier": "Andrea Fischbacher", "nation": "Austria", "id": 15, "previous_elo": 1553.7599426257498, "new_elo": 1563.6526807431687, "change": 9.892738117418958}, {"place": 8, "skier": "Leanne Smith", "nation": "USA", "id": 30, "previous_elo": 1314.8883099940572, "new_elo": 1340.2452127084853, "change": 25.356902714428088}, {"place": 9, "skier": "Maria H\u00f6fl-Riesch", "nation": "Germany", "id": 8, "previous_elo": 1702.0790099018604, "new_elo": 1701.4309683050362, "change": -0.6480415968242141}, {"place": 10, "skier": "Nicole Hosp", "nation": "Austria", "id": 32, "previous_elo": 1494.3281846792806, "new_elo": 1504.0586590547891, "change": 9.730474375508493}, {"place": 11, "skier": "Dominique Gisin", "nation": "Switzerland", "id": 7, "previous_elo": 1460.2418332909044, "new_elo": 1470.6356218474948, "change": 10.39378855659038}, {"place": 11, "skier": "Viktoria Rebensburg", "nation": "Germany", "id": 3, "previous_elo": 1521.2018185935322, "new_elo": 1527.385348652242, "change": 6.183530058709948}, {"place": 13, "skier": "Margret Altacher", "nation": "Austria", "id": 37, "previous_elo": 1271.939539068326, "new_elo": 1294.693566232342, "change": 22.75402716401595}, {"place": 14, "skier": "Nadja Jnglin-Kamer", "nation": "Switzerland", "id": 105, "previous_elo": 1461.3421050739864, "new_elo": 1468.7620798447826, "change": 7.419974770796216}, {"place": 15, "skier": "Elena Curtoni", "nation": "Italy", "id": 33, "previous_elo": 1249.2873959934495, "new_elo": 1271.35548532725, "change": 22.06808933380057}, {"place": 16, "skier": "Tina Maze", "nation": "Slovenia", "id": 16, "previous_elo": 1582.619223773453, "new_elo": 1579.781783873325, "change": -2.8374399001281745}, {"place": 17, "skier": "Daniela Merighetti", "nation": "Italy", "id": 25, "previous_elo": 1478.4857149903055, "new_elo": 1481.213168956334, "change": 2.7274539660284063}, {"place": 18, "skier": "Marie Jay Marchand-Arvier", "nation": "France", "id": 17, "previous_elo": 1447.5448656446756, "new_elo": 1451.3317015639038, "change": 3.786835919228224}, {"place": 19, "skier": "Laurenne Ross", "nation": "USA", "id": 91, "previous_elo": 1305.315120819954, "new_elo": 1318.6539891299694, "change": 13.338868310015414}, {"place": 20, "skier": "Marion Rolland", "nation": "France", "id": 39, "previous_elo": 1429.266033034166, "new_elo": 1432.0805212937476, "change": 2.8144882595815943}, {"place": 21, "skier": "Stacey Cook", "nation": "USA", "id": 41, "previous_elo": 1284.9819944506426, "new_elo": 1297.5166688734882, "change": 12.534674422845683}, {"place": 22, "skier": "Britt Janyk", "nation": "Canada", "id": 106, "previous_elo": 1364.5269855552754, "new_elo": 1369.906445821032, "change": 5.379460265756734}, {"place": 23, "skier": "Johanna Schnarf", "nation": "Italy", "id": 22, "previous_elo": 1391.750288030782, "new_elo": 1393.903846937143, "change": 2.153558906361013}, {"place": 24, "skier": "Regina Mader Sterz", "nation": "Austria", "id": 93, "previous_elo": 1306.8497906172831, "new_elo": 1314.2842229035186, "change": 7.434432286235506}, {"place": 25, "skier": "Fraenzi Aufdenblatten", "nation": "Switzerland", "id": 23, "previous_elo": 1394.70969027998, "new_elo": 1393.744638369023, "change": -0.965051910956845}, {"place": 25, "skier": "Jessica Lindell-Vikarby", "nation": "Sweden", "id": 14, "previous_elo": 1321.301963244707, "new_elo": 1325.9121096062174, "change": 4.610146361510488}, {"place": 27, "skier": "Lucia Recchia", "nation": "Italy", "id": 29, "previous_elo": 1412.2446146170537, "new_elo": 1408.222400633481, "change": -4.022213983572783}, {"place": 28, "skier": "Carolina Ruiz Castillo", "nation": "Spain", "id": 46, "previous_elo": 1342.4376443929034, "new_elo": 1342.5509913435071, "change": 0.11334695060372724}, {"place": 29, "skier": "Margot Bailet", "nation": "France", "id": 42, "previous_elo": 1293.963791656527, "new_elo": 1296.570421049168, "change": 2.6066293926410253}, {"place": 30, "skier": "Elisabeth G\u00f6rgl", "nation": "Austria", "id": 4, "previous_elo": 1597.6305557641683, "new_elo": 1577.7274226170452, "change": -19.90313314712307}, {"place": 31, "skier": "Martina Schild", "nation": "Switzerland", "id": 20, "previous_elo": 1344.4555202111071, "new_elo": 1340.9417558025289, "change": -3.513764408578254}, {"place": 32, "skier": "Marianne Kaufmann-Abderhalden", "nation": "Switzerland", "id": 88, "previous_elo": 1304.3095765884266, "new_elo": 1302.67107924863, "change": -1.638497339796686}, {"place": 33, "skier": "Ingrid Jacquemod", "nation": "France", "id": 107, "previous_elo": 1453.9728910196534, "new_elo": 1439.9243288146624, "change": -14.048562204990958}, {"place": 34, "skier": "Francesca Marsaglia", "nation": "Italy", "id": 35, "previous_elo": 1210.6986326363185, "new_elo": 1213.4317426679313, "change": 2.733110031612796}, {"place": 35, "skier": "Marusa Ferk", "nation": "Slovenia", "id": 47, "previous_elo": 1315.182327127288, "new_elo": 1309.2539356660964, "change": -5.9283914611917226}, {"place": 36, "skier": "Verena Stuffer", "nation": "Italy", "id": 31, "previous_elo": 1259.7673446763836, "new_elo": 1256.770877781013, "change": -2.9964668953705313}, {"place": 37, "skier": "Stefanie Moser", "nation": "Austria", "id": 40, "previous_elo": 1240.2399204185365, "new_elo": 1237.472750297473, "change": -2.767170121063373}, {"place": 38, "skier": "Denise Feierabend", "nation": "Switzerland", "id": 117, "previous_elo": 1295.3036411583057, "new_elo": 1287.3896307144234, "change": -7.914010443882262}, {"place": 39, "skier": "Chelsea Marshall", "nation": "USA", "id": 52, "previous_elo": 1281.2716521136, "new_elo": 1273.2374197282, "change": -8.034232385400173}, {"place": 40, "skier": "Enrica Cipriani", "nation": "Italy", "id": 206, "previous_elo": 1174.399673154443, "new_elo": 1172.5361117259283, "change": -1.8635614285146858}, {"place": 41, "skier": "Lotte Smiseth Sejersted", "nation": "Norway", "id": 34, "previous_elo": 1196.5554028256704, "new_elo": 1192.1187017397208, "change": -4.436701085949608}, {"place": 42, "skier": "Mariella Voglreiter", "nation": "Austria", "id": 51, "previous_elo": 1236.0802016903838, "new_elo": 1227.814444721747, "change": -8.265756968636879}, {"place": 43, "skier": "Gina Stechert", "nation": "Germany", "id": 215, "previous_elo": 1394.1775512305155, "new_elo": 1372.989577939165, "change": -21.187973291350545}, {"place": 44, "skier": "Andrea Dettling", "nation": "Switzerland", "id": 216, "previous_elo": 1371.6983302826736, "new_elo": 1351.0583027174944, "change": -20.640027565179253}, {"place": 45, "skier": "Isabelle Stiepel", "nation": "Germany", "id": 204, "previous_elo": 1218.1114695684894, "new_elo": 1207.608090262991, "change": -10.503379305498356}, {"place": 46, "skier": "Michaela Kirchgasser", "nation": "Austria", "id": 24, "previous_elo": 1507.9336075606543, "new_elo": 1475.053602367692, "change": -32.880005192962244}, {"place": 47, "skier": "Christina Staudinger", "nation": "Austria", "id": 45, "previous_elo": 1272.5666301038873, "new_elo": 1255.9065355501673, "change": -16.66009455372}, {"place": 48, "skier": "Marie-Pier Prefontaine", "nation": "Canada", "id": 69, "previous_elo": 1242.2613399397844, "new_elo": 1226.615360685309, "change": -15.645979254475378}, {"place": 49, "skier": "Georgia Simmerling", "nation": "Canada", "id": 217, "previous_elo": 1190.0686124850606, "new_elo": 1176.7896252646735, "change": -13.27898722038708}, {"place": 50, "skier": "Camilla Borsotti", "nation": "Italy", "id": 50, "previous_elo": 1182.2068044183854, "new_elo": 1168.272846197255, "change": -13.933958221130524}, {"place": 51, "skier": "Pamela Thorburn", "nation": "Great Britain", "id": 218, "previous_elo": 1215.0465410676002, "new_elo": 1197.8031351397271, "change": -17.243405927873027}, {"place": 52, "skier": "Maria Belen Simari Birkner", "nation": "Argentina", "id": 56, "previous_elo": 1134.8912628633182, "new_elo": 1121.4912427989514, "change": -13.4000200643668}]