[{"place": 1, "skier": "Marc Girardelli", "nation": "Luxembourg", "id": 568, "previous_elo": 1484.187364115268, "new_elo": 1490.000552744254, "change": 5.813188628985927}, {"place": 2, "skier": "Lars-Borje Eriksson", "nation": "Sweden", "id": 721, "previous_elo": 1318.7273165850888, "new_elo": 1327.5312875287557, "change": 8.803970943666855}, {"place": 3, "skier": "Pirmin Zurbriggen", "nation": "Switzerland", "id": 722, "previous_elo": 1490.1739617312974, "new_elo": 1493.2902286549502, "change": 3.116266923652802}, {"place": 4, "skier": "Markus Wasmeier", "nation": "Germany", "id": 617, "previous_elo": 1411.6018964041718, "new_elo": 1415.3979878284208, "change": 3.7960914242489707}, {"place": 5, "skier": "Luc Alphand", "nation": "France", "id": 505, "previous_elo": 1322.8669800225423, "new_elo": 1327.7289444060384, "change": 4.861964383496115}, {"place": 6, "skier": "Martin Hangl", "nation": "Switzerland", "id": 715, "previous_elo": 1325.5221771515328, "new_elo": 1329.0365288250002, "change": 3.514351673467445}, {"place": 7, "skier": "Franck Piccard", "nation": "France", "id": 582, "previous_elo": 1370.003248677078, "new_elo": 1371.061556550403, "change": 1.0583078733250204}, {"place": 8, "skier": "Peter Runggaldier", "nation": "Italy", "id": 459, "previous_elo": 1284.5641410280402, "new_elo": 1286.5854345265232, "change": 2.021293498482919}, {"place": 9, "skier": "Alberto Tomba", "nation": "Italy", "id": 523, "previous_elo": 1458.8334125862034, "new_elo": 1455.039106360128, "change": -3.7943062260753777}, {"place": 10, "skier": "Urs K\u00e4lin", "nation": "Switzerland", "id": 410, "previous_elo": 1286.454209726232, "new_elo": 1285.8717739949604, "change": -0.5824357312715165}, {"place": 11, "skier": "Helmut Mayer", "nation": "Austria", "id": 629, "previous_elo": 1401.5981560561547, "new_elo": 1396.7111561050192, "change": -4.886999951135522}, {"place": 12, "skier": "Franz Heinzer", "nation": "Switzerland", "id": 641, "previous_elo": 1367.5456305044702, "new_elo": 1362.2802612430562, "change": -5.26536926141398}, {"place": 13, "skier": "Niklas Henning", "nation": "Sweden", "id": 704, "previous_elo": 1304.791651633878, "new_elo": 1299.264850070251, "change": -5.526801563627032}, {"place": 13, "skier": "Peter Eigler", "nation": "Germany", "id": 705, "previous_elo": 1293.6060120552988, "new_elo": 1288.368198149159, "change": -5.237813906139763}, {"place": 15, "skier": "Guenther Mader", "nation": "Austria", "id": 503, "previous_elo": 1314.318738181124, "new_elo": 1306.6270294714604, "change": -7.691708709663544}]