[{"place": 1, "skier": "Hannu Manninen", "nation": "Finland", "id": 110, "previous_elo": 1558.984879626638, "new_elo": 1571.176774482699, "change": 12.191894856061026}, {"place": 2, "skier": "Bjarte Engen Vik", "nation": "Norway", "id": 294, "previous_elo": 1667.3086913402674, "new_elo": 1671.4323916071737, "change": 4.123700266906326}, {"place": 3, "skier": "Urs Kunz", "nation": "Switzerland", "id": 315, "previous_elo": 1243.2702820304903, "new_elo": 1267.7611499362456, "change": 24.490867905755294}, {"place": 4, "skier": "Tapio Nurmela", "nation": "Finland", "id": 321, "previous_elo": 1391.3510003980712, "new_elo": 1403.523863434765, "change": 12.172863036693798}, {"place": 5, "skier": "Denis Tishagin", "nation": "Russia", "id": 298, "previous_elo": 1295.543109593634, "new_elo": 1310.4535175754284, "change": 14.910407981794378}, {"place": 6, "skier": "Jari Mantila", "nation": "Finland", "id": 270, "previous_elo": 1496.8564132443298, "new_elo": 1496.1839199868507, "change": -0.6724932574791183}, {"place": 7, "skier": "Dmitri Sinitzyn", "nation": "Russia", "id": 296, "previous_elo": 1300.0, "new_elo": 1308.1538171788277, "change": 8.153817178827694}, {"place": 8, "skier": "Matthias Loo\u00df", "nation": "Germany", "id": 293, "previous_elo": 1312.42296231612, "new_elo": 1316.570408168566, "change": 4.147445852446026}, {"place": 9, "skier": "Felix Gottwald", "nation": "Austria", "id": 104, "previous_elo": 1381.335674816675, "new_elo": 1377.9261354665443, "change": -3.4095393501306717}, {"place": 10, "skier": "Vladimir Lysenin", "nation": "Russia", "id": 285, "previous_elo": 1300.0, "new_elo": 1298.4274249270115, "change": -1.5725750729884567}, {"place": 11, "skier": "Samppa Lajunen", "nation": "Finland", "id": 244, "previous_elo": 1547.2700828821962, "new_elo": 1527.6420447886535, "change": -19.628038093542727}, {"place": 12, "skier": "Robert Stadelmann", "nation": "Austria", "id": 327, "previous_elo": 1230.5870013039755, "new_elo": 1226.616351042827, "change": -3.970650261148421}, {"place": 13, "skier": "Milan Ku\u010dera", "nation": "Czechia", "id": 284, "previous_elo": 1324.0983859779976, "new_elo": 1311.3110278124589, "change": -12.787358165538762}, {"place": 14, "skier": "Topi Sarparanta", "nation": "Finland", "id": 333, "previous_elo": 1344.4815143520473, "new_elo": 1327.177882628796, "change": -17.30363172325133}, {"place": 15, "skier": "Walerij Stoljarov", "nation": "Russia", "id": 300, "previous_elo": 1349.2760367760943, "new_elo": 1328.4293256216893, "change": -20.846711154405057}]