{"columns":[{"name":"Exp","datatype":"Int64","bit_settings":"","values":[1,2,3,4,5,6,7,8,9,10,11,12,13,14,15,16,17,18,19,20,21,22,23,24,25,26,27,28,29,30,31,32,33,34,35,36,37,38,39,40,41,42,43,44,45,46,47,48,49,50,51,52,53,54,55,56,57,58,59,60,61,62,63,64,65,66,67,68,69,70,71,72,73,74,75,76,77,78,79,80,81,82,83,84,85,86,87,88,89,90,91,92,93,94,95,96,97,98,99,100,101,102,103,104,105,106,107,108,109,110,111]},{"name":"Date","datatype":"String","bit_settings":"","values":["2005-02-17","2005-02-22","2005-02-25","2007-02-22","2007-02-24","2007-02-28","2007-12-02","2008-11-22","2008-11-30","2008-12-13","2009-02-20","2009-02-24","2009-03-01","2009-11-21","2009-11-28","2009-11-29","2009-12-12","2009-12-13","2010-01-22","2010-01-23","2010-02-05","2010-02-06","2010-02-15","2010-11-20","2010-11-26","2010-11-27","2010-12-11","2011-01-22","2011-01-23","2011-02-27","2011-03-01","2011-11-19","2011-11-25","2011-11-26","2012-11-24","2012-11-30","2012-12-01","2012-12-02","2012-12-02","2013-02-21","2013-02-27","2013-11-29","2013-11-30","2013-12-01","2013-12-01","2014-01-18","2014-01-19","2014-02-09","2014-02-14","2014-02-19","2014-11-30","2014-12-05","2014-12-06","2014-12-13","2014-12-14","2014-12-20","2015-01-03","2015-01-04","2015-01-06","2015-01-07","2015-01-08","2015-01-10","2015-01-11","2015-01-11","2015-02-15","2015-02-19","2015-02-21","2015-02-25","2015-11-27","2015-11-28","2015-11-29","2015-11-29","2015-12-12","2016-01-01","2016-01-02","2016-01-03","2016-01-05","2016-01-06","2016-01-08","2016-01-09","2016-01-10","2016-01-10","2016-02-13","2016-02-14","2016-11-26","2016-11-27","2016-12-02","2016-12-03","2016-12-04","2016-12-04","2016-12-10","2016-12-11","2016-12-17","2016-12-31","2017-01-01","2017-01-03","2017-03-01","2017-11-24","2017-11-25","2017-11-26","2017-11-26","2017-12-09","2017-12-10","2017-12-16","2017-12-17","2018-01-28","2018-02-13","2018-02-16","2018-02-21","2018-12-16","2019-02-27"]},{"name":"City","datatype":"String","bit_settings":"","values":["Oberstdorf","Oberstdorf","Oberstdorf","Sapporo","Sapporo","Sapporo","Ruka ","Gällivare","Ruka ","Davos","Liberec","Liberec","Liberec","Beitostølen","Ruka ","Ruka ","Davos","Davos","Rybinsk","Rybinsk","Canmore, AB","Canmore, AB","Whistler, BC","Gällivare","Ruka ","Ruka ","Davos","Otepää","Otepää","Holmenkollen","Holmenkollen","Sjusjøen","Ruka ","Ruka ","Gällivare","Ruka ","Ruka ","Ruka ","Nordic Opening","Val di Fiemme","Val di Fiemme","Ruka ","Ruka ","Ruka ","Nordic Opening","Szklarska Poręba","Szklarska Poręba","Sóchi","Sóchi","Sóchi","Ruka ","Lillehammer","Lillehammer","Davos","Davos","Davos","Oberstdorf","Oberstdorf","Val Müstair","Toblach / Dobbiaco","Toblach / Dobbiaco","Val di Fiemme","Tour de Ski","Val di Fiemme","Östersund","Falun","Falun","Falun","Ruka ","Ruka ","Nordic Opening","Ruka ","Davos","Lenzerheide","Lenzerheide","Lenzerheide","Oberstdorf","Oberstdorf","Toblach / Dobbiaco","Val di Fiemme","Tour de Ski","Val di Fiemme","Falun","Falun","Ruka ","Ruka ","Lillehammer","Lillehammer","Nordic Opening","Lillehammer","Davos","Davos","La Clusaz","Val Müstair","Val Müstair","Oberstdorf","Lahti","Ruka ","Ruka ","Nordic Opening","Ruka ","Davos","Davos","Toblach / Dobbiaco","Toblach / Dobbiaco","Seefeld in Tirol","Pyeongchang ","Pyeongchang ","Pyeongchang ","Davos","Seefeld in Tirol"]},{"name":"Country","datatype":"String","bit_settings":"","values":["Germany","Germany","Germany","Japan","Japan","Japan","Finland","Sweden","Finland","Switzerland","Czechia","Czechia","Czechia","Norway","Finland","Finland","Switzerland","Switzerland","Russia","Russia","Canada","Canada","Canada","Sweden","Finland","Finland","Switzerland","Estonia","Estonia","Norway","Norway","Norway","Finland","Finland","Sweden","Finland","Finland","Finland","FIS","Italy","Italy","Finland","Finland","Finland","FIS","Poland","Poland","Russia","Russia","Russia","Finland","Norway","Norway","Switzerland","Switzerland","Switzerland","Germany","Germany","Switzerland","Italy","Italy","Italy","FIS","Italy","Sweden","Sweden","Sweden","Sweden","Finland","Finland","FIS","Finland","Switzerland","Switzerland","Switzerland","Switzerland","Germany","Germany","Italy","Italy","FIS","Italy","Sweden","Sweden","Finland","Finland","Norway","Norway","FIS","Norway","Switzerland","Switzerland","France","Switzerland","Switzerland","Germany","Finland","Finland","Finland","FIS","Finland","Switzerland","Switzerland","Italy","Italy","Austria","South Korea","South Korea","South Korea","Switzerland","Austria"]},{"name":"Event","datatype":"String","bit_settings":"","values":["World Championship","World Championship","World Championship","World Championship","World Championship","World Championship","World Cup","World Cup","World Cup","World Cup","World Championship","World Championship","World Championship","World Cup","World Cup","World Cup","World Cup","World Cup","World Cup","World Cup","World Cup","World Cup","Olympic Winter Games","World Cup","Nordic Opening","Nordic Opening","World Cup","World Cup","World Cup","World Championship","World Championship","World Cup","Nordic Opening","Nordic Opening","World Cup","Nordic Opening","Nordic Opening","Nordic Opening","Nordic Opening","World Championship","World Championship","Nordic Opening","Nordic Opening","Nordic Opening","Nordic Opening","World Cup","World Cup","Olympic Winter Games","Olympic Winter Games","Olympic Winter Games","World Cup","Nordic Opening","Nordic Opening","World Cup","World Cup","World Cup","Tour de Ski","Tour de Ski","Tour de Ski","Tour de Ski","Tour de Ski","Tour de Ski","Tour de Ski","Tour de Ski","World Cup","World Championship","World Championship","World Championship","Nordic Opening","Nordic Opening","Nordic Opening","Nordic Opening","World Cup","Tour de Ski","Tour de Ski","Tour de Ski","Tour de Ski","Tour de Ski","Tour de Ski","Tour de Ski","Tour de Ski","Tour de Ski","World Cup","World Cup","World Cup","World Cup","Nordic Opening","Nordic Opening","Nordic Opening","Nordic Opening","World Cup","World Cup","World Cup","Tour de Ski","Tour de Ski","Tour de Ski","World Championship","Nordic Opening","Nordic Opening","Nordic Opening","Nordic Opening","World Cup","World Cup","World Cup","World Cup","World Cup","Olympic Winter Games","Olympic Winter Games","Olympic Winter Games","World Cup","World Championship"]},{"name":"Distance","datatype":"String","bit_settings":"","values":["15","Sprint","Ts","Sprint","Duathlon","15","15","15","15","15","15","Sprint","50","15","Sprint","15","15","Sprint","Sprint","Duathlon","15","Sprint","15","15","Sprint","10","15","15","Sprint","Duathlon","15","15","Sprint","10","15","Sprint","10","15","Stage","Sprint","15","Sprint","10","15","Stage","Sprint","15","Duathlon","15","Ts","15","Sprint","10","15","Sprint","15","4","15","Sprint","10","25","15","Stage","9","15","Sprint","Duathlon","15","Sprint","10","Stage","15","30","Sprint","30","10","Sprint","15","10","15","Stage","9","10","15","Sprint","15","Sprint","10","Stage","15","30","Sprint","15","Sprint","10","Duathlon","15","Sprint","15","Stage","15","Sprint","15","15","15","15","Sprint","15","Ts","15","15"]},{"name":"MS","datatype":"Int64","bit_settings":"","values":[0,0,0,0,1,0,0,0,0,0,0,0,1,0,0,0,0,0,0,1,0,0,0,0,0,0,0,0,0,1,0,0,0,0,0,0,0,0,0,0,0,0,0,0,0,0,1,1,0,0,0,0,0,0,0,0,0,0,0,0,0,1,0,0,0,0,1,0,0,0,0,0,0,0,1,0,0,1,0,1,0,0,0,1,0,0,0,0,0,0,0,0,1,0,1,1,0,0,0,0,0,0,0,0,0,1,0,0,0,0,0]},{"name":"Technique","datatype":"String","bit_settings":"","values":["F","C","F","C","P","F","C","F","C","C","C","F","F","F","C","C","F","F","F","P","F","C","F","F","C","C","C","C","C","P","C","F","C","F","F","C","F","C","N/A","C","F","C","C","F","N/A","F","C","P","C","C","C","F","F","C","F","F","F","C","F","C","F","C","N/A","F","F","C","P","F","C","F","N/A","C","F","F","C","F","C","C","F","C","N/A","F","C","F","C","C","C","F","N/A","C","F","F","F","F","C","P","C","C","C","N/A","F","F","F","F","C","F","C","F","F","F","C"]},{"name":"Place","datatype":"Int64","bit_settings":"","values":[85,74,22,57,55,50,84,61,71,54,53,56,41,81,90,77,71,93,40,21,34,66,50,72,123,81,61,47,73,59,46,86,101,99,72,83,71,60,64,71,78,88,80,66,71,58,14,52,41,19,67,101,45,62,87,55,29,42,66,37,40,41,37,31,31,63,39,39,61,47,39,38,41,91,51,51,68,42,55,34,42,47,61,55,75,36,83,22,45,49,50,78,23,58,31,36,48,75,51,60,68,85,45,34,40,42,60,36,23,78,40]},{"name":"Season","datatype":"Int64","bit_settings":"SORTED_ASC","values":[2005,2005,2005,2007,2007,2007,2008,2009,2009,2009,2009,2009,2009,2010,2010,2010,2010,2010,2010,2010,2010,2010,2010,2011,2011,2011,2011,2011,2011,2011,2011,2012,2012,2012,2013,2013,2013,2013,2013,2013,2013,2014,2014,2014,2014,2014,2014,2014,2014,2014,2015,2015,2015,2015,2015,2015,2015,2015,2015,2015,2015,2015,2015,2015,2015,2015,2015,2015,2016,2016,2016,2016,2016,2016,2016,2016,2016,2016,2016,2016,2016,2016,2016,2016,2017,2017,2017,2017,2017,2017,2017,2017,2017,2017,2017,2017,2017,2018,2018,2018,2018,2018,2018,2018,2018,2018,2018,2018,2018,2019,2019]},{"name":"Race","datatype":"Int64","bit_settings":"","values":[21,23,25,25,27,28,6,1,4,7,28,30,33,1,3,4,7,8,22,23,25,26,27,1,3,4,9,24,25,32,33,1,3,4,1,3,4,5,6,27,30,1,2,3,4,21,22,25,27,29,2,3,4,7,8,9,11,12,13,14,15,16,17,18,25,26,27,29,1,2,3,4,7,11,12,13,14,15,16,17,18,19,27,28,1,2,3,4,5,6,7,8,9,11,12,13,33,1,2,3,4,7,8,9,10,23,25,26,28,10,30]},{"name":"Age","datatype":"String","bit_settings":"","values":["18.55715263518138","18.570841889117045","18.579055441478438","20.569472963723477","20.57494866529774","20.585900068446268","21.34428473648186","22.31895961670089","22.340862422997947","22.376454483230663","22.56536618754278","22.576317590691307","22.590006844626966","23.315537303216974","23.3347022587269","23.33744010951403","23.373032169746747","23.37577002053388","23.485284052019164","23.488021902806295","23.523613963039015","23.526351813826146","23.550992470910334","24.312114989733058","24.32854209445585","24.331279945242983","24.369609856262834","24.484599589322382","24.487337440109513","24.583162217659137","24.588637919233403","25.308692676249144","25.325119780971935","25.32785763175907","26.324435318275153","26.340862422997947","26.34360027378508","26.34633812457221","26.34633812457221","26.56810403832991","26.584531143052704","27.33744010951403","27.340177960301162","27.342915811088297","27.342915811088297","27.474332648870636","27.477070499657767","27.534565366187543","27.548254620123203","27.561943874058862","28.33949349760438","28.35318275154004","28.355920602327174","28.375085557837096","28.37782340862423","28.39425051334702","28.432580424366872","28.435318275154003","28.44079397672827","28.4435318275154","28.44626967830253","28.451745379876797","28.45448323066393","28.45448323066393","28.550308008213552","28.56125941136208","28.566735112936346","28.577686516084874","29.3305954825462","29.333333333333332","29.336071184120463","29.336071184120463","29.371663244353183","29.426420260095824","29.429158110882955","29.43189596167009","29.437371663244353","29.440109514031484","29.44558521560575","29.44832306639288","29.451060917180012","29.451060917180012","29.544147843942504","29.546885694729635","30.32991101984942","30.33264887063655","30.34633812457221","30.34907597535934","30.351813826146476","30.351813826146476","30.368240930869266","30.3709787816564","30.38740588637919","30.425735797399042","30.428473648186174","30.433949349760436","30.590006844626966","31.32375085557837","31.326488706365502","31.329226557152634","31.329226557152634","31.364818617385353","31.367556468172484","31.383983572895275","31.38672142368241","31.50171115674196","31.54551676933607","31.55373032169747","31.567419575633128","32.38329911019849","32.58316221765914"]},{"name":"Elo","datatype":"Float64","bit_settings":"","values":[1274.0238988950052,1241.3428730078488,1225.905284705646,1224.20639313053,1207.5017926825467,1234.0518568885811,1214.2980033519616,1228.4298299055108,1218.6447389860932,1222.5225895327524,1219.947813606344,1246.9234957372514,1246.7679076263341,1239.5557226939582,1209.4576414355054,1200.9356054816587,1196.6362347087852,1174.6732562560544,1165.779005330432,1161.7220907791593,1187.3517296441255,1170.8742425423914,1189.8432450412913,1208.5495003481542,1175.7115309598255,1175.9302984162516,1175.7105319914217,1182.5928166860015,1164.4020974881857,1164.1284590216237,1172.4520252081406,1173.7565124092794,1165.9437719572188,1156.6598270637237,1176.3109102098244,1182.040752600043,1190.3858160885968,1193.2595714117506,1191.5040621496648,1203.6874661731104,1186.7079461468074,1205.0406617787476,1210.8818049521203,1215.9539606563017,1214.7587215890042,1198.1364271899954,1230.5289215447433,1221.768226938674,1238.3991662470187,1229.955212411813,1237.653832354332,1215.3764757297872,1257.9254557417648,1249.5736621773854,1219.2559692031011,1222.6404902864806,1270.038392187232,1292.4144793140676,1278.8437507194317,1292.0864747728394,1289.0958237508316,1280.7901161689203,1275.2144163528253,1277.2257199521132,1309.2674623794514,1309.1308658215685,1305.4962286751443,1315.8133683081699,1322.586056533082,1343.1787661343672,1355.1587557783876,1366.8159919379127,1369.366686762711,1332.761384310066,1336.3388601132215,1337.068000248596,1314.8239005409869,1316.8687213999526,1301.2601364146526,1307.2221090913604,1301.5499889701146,1290.5966604622593,1286.1224495818674,1286.7267250275775,1268.4000439570375,1293.8903470419007,1271.7864621452088,1315.8497975002088,1323.7173227208991,1326.5124788575438,1320.5725318031518,1293.566069645581,1317.029896510203,1312.0423105733723,1331.343183743963,1332.541109297198,1328.459262391588,1322.5400496556833,1341.6586986029477,1331.1230904216475,1313.0156508304322,1284.9827228860875,1306.4712714191216,1328.6693036260556,1337.0401465048342,1347.634238129998,1325.839147795783,1351.440546724584,1333.935984058856,1305.5334133434571,1315.0095222388413]},{"name":"Distance_Elo","datatype":"Float64","bit_settings":"","values":[1273.5095424075748,1273.5095424075748,1273.5095424075748,1273.5095424075748,1258.1121013010695,1279.4326731605488,1249.822555848129,1256.1281224411273,1242.8308263600172,1245.6430957321668,1242.5055585468601,1242.5055585468601,1243.5379831518292,1236.7568734514668,1236.7568734514668,1224.5118124934745,1218.441674742079,1218.441674742079,1218.441674742079,1213.1768153993146,1236.7812114649903,1236.7812114649903,1252.122854164694,1255.222077330564,1255.222077330564,1244.4248319422356,1239.0588869891835,1241.7638402404998,1241.7638402404998,1237.1032868123323,1240.8111366387636,1226.0274143164454,1226.0274143164454,1206.703931280469,1215.1184876753707,1215.1184876753707,1218.452507646463,1218.8137980108595,1215.0154966021155,1215.0154966021155,1198.184873998499,1213.4571428987242,1214.5949315442112,1217.790799339599,1214.3122114610371,1214.3122114610371,1246.829714409421,1238.7676646500797,1256.3356643333625,1256.3356643333625,1255.3700462285217,1255.3700462285217,1289.6182758830378,1278.3782409325477,1278.3782409325477,1276.383938233248,1315.621266343565,1329.9037765871146,1329.9037765871146,1338.3997069706706,1333.0034562898616,1322.7459959006344,1315.4673505277162,1316.1647744785976,1344.929967962705,1344.929967962705,1339.75733459928,1345.9146993879265,1339.0274944797375,1350.6402689409117,1358.3998368692053,1366.3431249689763,1369.615099333061,1369.615099333061,1366.927341313558,1362.3647510048393,1362.3647510048393,1361.3886663356407,1343.9445792664926,1347.8209658737699,1340.5523436235853,1328.2467537945067,1318.765007736814,1315.3085625941465,1313.0122782050244,1332.675558682497,1332.675558682497,1367.1231952713129,1368.7290096798017,1366.0100828147279,1357.8591126126878,1357.8591126126878,1374.92700656779,1374.92700656779,1386.6240269433588,1384.609339770054,1374.4766657999396,1363.3051659299485,1368.9940095667926,1352.6858361845386,1329.473991378779,1329.473991378779,1343.1733447292852,1360.3559370853034,1364.7342238689605,1370.490088948388,1370.490088948388,1389.1831941348532,1389.1831941348532,1344.249613139549,1348.3219106256051]},{"name":"Distance_C_Pelo","datatype":"Float64","bit_settings":"","values":[null,null,null,null,null,null,1300.0,1261.4658719381732,1261.4658719381732,1243.0684091848732,1243.7721740777056,1239.1479117281526,1239.1479117281526,1239.1479117281526,1239.1479117281526,1248.2757249689298,1228.6374004583417,1228.6374004583417,1228.6374004583417,1228.6374004583417,1228.6374004583417,1228.6374004583417,1228.6374004583417,1228.6374004583417,1228.6374004583417,1239.3417903895904,1225.439155696988,1218.4222286432587,1223.5493337962982,1223.5493337962982,1223.5493337962982,1239.033513384956,1239.033513384956,1239.033513384956,1239.033513384956,1239.033513384956,1239.033513384956,1239.033513384956,1234.6840428907822,1234.6840428907822,1234.6840428907822,1234.6840428907822,1244.4814364571648,1236.9228659123096,1236.9228659123096,1236.9228659123096,1236.9228659123096,1274.2044519968274,1274.2044519968274,1289.848483899627,1291.3712113146828,1274.1008939280446,1274.1008939280446,1274.1008939280446,1258.5397798259548,1258.5397798259548,1258.5397798259548,1258.5397798259548,1283.4156003780586,1283.4156003780586,1297.5425131571735,1297.5425131571735,1284.789608722218,1284.789608722218,1284.789608722218,1284.789608722218,1284.789608722218,1284.789608722218,1284.789608722218,1284.789608722218,1284.789608722218,1287.0711674138852,1302.591931526325,1302.591931526325,1302.591931526325,1303.4150511889256,1303.4150511889256,1303.4150511889256,1303.3752325764517,1303.3752325764517,1307.711137858641,1307.711137858641,1307.711137858641,1295.1046666937332,1295.1046666937332,1295.8389666896733,1320.2239662368297,1320.2239662368297,1320.2239662368297,1320.2239662368297,1319.4984547123981,1319.4984547123981,1319.4984547123981,1319.4984547123981,1319.4984547123981,1336.4914457527536,1336.4914457527536,1325.1445994810083,1325.1445994810083,1339.6791279365757,1339.6791279365757,1339.6791279365757,1339.6791279365757,1339.6791279365757,1339.6791279365757,1344.6514517918763,1344.6514517918763,1344.6514517918763,1344.6514517918763,1344.6514517918763,1337.9537340230947]},{"name":"Distance_F_Pelo","datatype":"Float64","bit_settings":"","values":[1300.0,1268.3940433175487,1268.3940433175487,1268.3940433175487,1268.3940433175487,1273.1349368199164,1296.762546032132,1296.762546032132,1287.302219714877,1287.302219714877,1287.302219714877,1287.302219714877,1287.302219714877,1286.003677019117,1262.2148564611437,1262.2148564611437,1262.2148564611437,1248.082515971726,1248.082515971726,1248.082515971726,1248.082515971726,1266.8839656338075,1266.8839656338075,1280.7462251711759,1268.7430180670356,1268.7430180670356,1268.7430180670356,1268.7430180670356,1268.7430180670356,1268.7430180670356,1268.7430180670356,1273.4315653569802,1241.7546878558849,1241.7546878558849,1228.787473053965,1220.7544757203354,1220.7544757203354,1221.3525160954339,1221.3525160954339,1221.3525160954339,1221.3525160954339,1218.3908811120423,1218.3908811120423,1218.3908811120423,1218.5688962173008,1218.5688962173008,1218.5688962173008,1218.5688962173008,1218.5688962173008,1218.5688962173008,1218.5688962173008,1218.5688962173008,1230.7835617847056,1261.1252735197834,1261.1252735197834,1261.1252735197834,1258.1147634276874,1290.743566616582,1290.743566616582,1290.743566616582,1290.743566616582,1284.7293429331958,1284.7293429331958,1284.7293429331958,1283.4453842651046,1310.0645376952225,1310.0645376952225,1310.0645376952225,1315.8484881246668,1315.8484881246668,1328.628281459605,1328.628281459605,1328.628281459605,1333.5681592189676,1333.5681592189676,1333.5681592189676,1327.481731663615,1327.481731663615,1327.481731663615,1307.4881741813485,1307.4881741813485,1307.4881741813485,1292.975183817027,1292.975183817027,1291.2067216140406,1291.2067216140406,1291.2067216140406,1291.2067216140406,1329.492840723437,1329.492840723437,1329.492840723437,1322.0366877025876,1322.0366877025876,1342.0817376340399,1342.0817376340399,1342.0817376340399,1342.0817376340399,1342.0817376340399,1342.0817376340399,1342.0817376340399,1335.7694769889338,1313.302462730777,1313.302462730777,1325.6181260585852,1339.4657513571042,1339.4657513571042,1345.1217911256745,1345.1217911256745,1363.9257117173795,1354.3368549597726,1325.9430767011334]},{"name":"Sprint_Elo","datatype":"Float64","bit_settings":"","values":[null,1260.9027346956848,1260.9027346956848,1253.241899074427,1253.241899074427,1253.241899074427,1253.241899074427,1253.241899074427,1253.241899074427,1253.241899074427,1253.241899074427,1284.486538620664,1284.486538620664,1284.486538620664,1249.998162627057,1249.998162627057,1249.998162627057,1218.9439086614734,1207.5694045326213,1207.5694045326213,1207.5694045326213,1188.3036743301222,1188.3036743301222,1188.3036743301222,1159.7678224679291,1159.7678224679291,1159.7678224679291,1159.7678224679291,1141.391942376716,1141.391942376716,1141.391942376716,1141.391942376716,1151.8544664437638,1151.8544664437638,1151.8544664437638,1174.7013429230412,1174.7013429230412,1174.7013429230412,1174.7013429230412,1198.6868685409777,1198.6868685409777,1207.690330204175,1207.690330204175,1207.690330204175,1207.690330204175,1193.270497556217,1193.270497556217,1193.270497556217,1193.270497556217,1193.270497556217,1193.270497556217,1184.1329356269064,1184.1329356269064,1184.1329356269064,1162.932790320901,1162.932790320901,1162.932790320901,1162.932790320901,1156.6548975341486,1156.6548975341486,1156.6548975341486,1156.6548975341486,1156.6548975341486,1156.6548975341486,1156.6548975341486,1191.7009981626966,1191.7009981626966,1191.7009981626966,1230.093782529394,1230.093782529394,1230.093782529394,1230.093782529394,1230.093782529394,1201.6625363057478,1201.6625363057478,1201.6625363057478,1181.5915301681894,1181.5915301681894,1181.5915301681894,1181.5915301681894,1181.5915301681894,1181.5915301681894,1181.5915301681894,1181.5915301681894,1190.1368882899485,1190.1368882899485,1171.328056496938,1171.328056496938,1171.328056496938,1171.328056496938,1171.328056496938,1163.0048999881058,1163.0048999881058,1167.8583640867546,1167.8583640867546,1167.8583640867546,1167.8583640867546,1207.9657800761458,1207.9657800761458,1207.9657800761458,1207.9657800761458,1198.8012940665487,1198.8012940665487,1198.8012940665487,1198.8012940665487,1198.8012940665487,1196.533475312187,1196.533475312187,1196.533475312187,1196.533475312187,1196.533475312187]},{"name":"Sprint_C_Elo","datatype":"Float64","bit_settings":"","values":[null,1256.934746349281,1256.934746349281,1248.5049062651392,1248.5049062651392,1248.5049062651392,1248.5049062651392,1248.5049062651392,1248.5049062651392,1248.5049062651392,1248.5049062651392,1248.5049062651392,1248.5049062651392,1248.5049062651392,1222.8289871116388,1222.8289871116388,1222.8289871116388,1222.8289871116388,1222.8289871116388,1222.8289871116388,1222.8289871116388,1201.6456720385572,1201.6456720385572,1201.6456720385572,1148.8954471137479,1148.8954471137479,1148.8954471137479,1148.8954471137479,1123.919166302506,1123.919166302506,1123.919166302506,1123.919166302506,1134.3409300666515,1134.3409300666515,1134.3409300666515,1160.497331143484,1160.497331143484,1160.497331143484,1160.497331143484,1189.4230725095097,1189.4230725095097,1194.7061115513457,1194.7061115513457,1194.7061115513457,1194.7061115513457,1194.7061115513457,1194.7061115513457,1194.7061115513457,1194.7061115513457,1194.7061115513457,1194.7061115513457,1194.7061115513457,1194.7061115513457,1194.7061115513457,1194.7061115513457,1194.7061115513457,1194.7061115513457,1194.7061115513457,1194.7061115513457,1194.7061115513457,1194.7061115513457,1194.7061115513457,1194.7061115513457,1194.7061115513457,1194.7061115513457,1242.4952346578118,1242.4952346578118,1242.4952346578118,1269.0456431951818,1269.0456431951818,1269.0456431951818,1269.0456431951818,1269.0456431951818,1269.0456431951818,1269.0456431951818,1269.0456431951818,1229.6827169870544,1229.6827169870544,1229.6827169870544,1229.6827169870544,1229.6827169870544,1229.6827169870544,1229.6827169870544,1229.6827169870544,1215.0752805691147,1215.0752805691147,1177.828122507611,1177.828122507611,1177.828122507611,1177.828122507611,1177.828122507611,1177.828122507611,1177.828122507611,1177.828122507611,1177.828122507611,1177.828122507611,1177.828122507611,1214.949037862949,1214.949037862949,1214.949037862949,1214.949037862949,1214.949037862949,1214.949037862949,1214.949037862949,1214.949037862949,1214.949037862949,1206.1449653953837,1206.1449653953837,1206.1449653953837,1206.1449653953837,1206.1449653953837]},{"name":"Sprint_F_Elo","datatype":"Float64","bit_settings":"","values":[null,null,null,null,null,null,null,null,null,null,null,1319.92193356824,1319.92193356824,1319.92193356824,1319.92193356824,1319.92193356824,1319.92193356824,1242.2443209764547,1219.5930909429492,1219.5930909429492,1219.5930909429492,1219.5930909429492,1219.5930909429492,1219.5930909429492,1219.5930909429492,1219.5930909429492,1219.5930909429492,1219.5930909429492,1219.5930909429492,1219.5930909429492,1219.5930909429492,1219.5930909429492,1219.5930909429492,1219.5930909429492,1219.5930909429492,1219.5930909429492,1219.5930909429492,1219.5930909429492,1219.5930909429492,1219.5930909429492,1219.5930909429492,1219.5930909429492,1219.5930909429492,1219.5930909429492,1219.5930909429492,1213.305966065379,1213.305966065379,1213.305966065379,1213.305966065379,1213.305966065379,1213.305966065379,1188.9629355983975,1188.9629355983975,1188.9629355983975,1159.5274259704,1159.5274259704,1159.5274259704,1159.5274259704,1150.9177655612148,1150.9177655612148,1150.9177655612148,1150.9177655612148,1150.9177655612148,1150.9177655612148,1150.9177655612148,1150.9177655612148,1150.9177655612148,1150.9177655612148,1150.9177655612148,1150.9177655612148,1150.9177655612148,1150.9177655612148,1150.9177655612148,1145.8895800935554,1145.8895800935554,1145.8895800935554,1145.8895800935554,1145.8895800935554,1145.8895800935554,1145.8895800935554,1145.8895800935554,1145.8895800935554,1145.8895800935554,1145.8895800935554,1145.8895800935554,1145.8895800935554,1145.8895800935554,1145.8895800935554,1145.8895800935554,1145.8895800935554,1145.8895800935554,1159.1788967095465,1159.1788967095465,1164.010597110677,1164.010597110677,1164.010597110677,1164.010597110677,1164.010597110677,1164.010597110677,1164.010597110677,1164.010597110677,1177.899116000395,1177.899116000395,1177.899116000395,1177.899116000395,1177.899116000395,1177.899116000395,1177.899116000395,1177.899116000395,1177.899116000395,1177.899116000395]},{"name":"Classic_Elo","datatype":"Float64","bit_settings":"","values":[null,1267.1419706333068,1267.1419706333068,1257.6853385061358,1257.6853385061358,1257.6853385061358,1230.2072002987234,1240.6761202539149,1227.2727055965772,1228.482598403703,1224.6945023784747,1224.6945023784747,1224.6945023784747,1224.6945023784747,1204.5280261049609,1194.1021992824346,1194.1021992824346,1194.1021992824346,1194.1021992824346,1194.1021992824346,1194.1021992824346,1175.9533758804178,1175.9533758804178,1175.9533758804178,1160.0864225433127,1159.16632834254,1158.2843092750024,1166.1664589507736,1148.752011755723,1148.752011755723,1157.244674638484,1178.6579734427114,1166.206434230357,1166.206434230357,1166.206434230357,1187.683111185223,1187.683111185223,1187.8618366117328,1187.8618366117328,1203.697832960537,1203.697832960537,1213.8149340645552,1214.6951571921159,1214.6951571921159,1214.6951571921159,1214.6951571921159,1244.8613401001662,1244.8613401001662,1258.667127469122,1248.1561635783153,1247.5007057128712,1247.5007057128712,1247.5007057128712,1236.3160512465424,1236.3160512465424,1236.3160512465424,1236.3160512465424,1259.6729391761578,1259.6729391761578,1273.1015528069481,1273.1015528069481,1263.099596715406,1263.099596715406,1263.099596715406,1263.099596715406,1274.3135050833714,1274.3135050833714,1274.3135050833714,1289.3134625227249,1289.3134625227249,1289.3134625227249,1304.8709147885934,1304.8709147885934,1304.8709147885934,1306.4287122843123,1306.4287122843123,1280.4202373673252,1281.4642743430416,1281.4642743430416,1285.9268576665936,1285.9268576665936,1285.9268576665936,1277.990708658072,1277.990708658072,1259.5340107478423,1285.9662130738907,1259.8963363558455,1259.8963363558455,1259.8963363558455,1266.3832082370243,1266.3832082370243,1266.3832082370243,1266.3832082370243,1266.3832082370243,1287.7697566968134,1287.7697566968134,1286.602140681995,1287.7221122824099,1310.4317069261297,1310.4317069261297,1310.4317069261297,1310.4317069261297,1310.4317069261297,1310.4317069261297,1317.6376253131534,1317.6376253131534,1292.7347449436438,1292.7347449436438,1292.7347449436438,1292.7347449436438,1303.341532456137]},{"name":"Freestyle_Elo","datatype":"Float64","bit_settings":"","values":[1267.8876759323325,1267.8876759323325,1246.39252518127,1254.4336464040796,1254.4336464040796,1278.715475578524,1281.9081542417455,1274.279205111635,1274.279205111635,1274.279205111635,1274.279205111635,1293.526243627923,1288.3177987564457,1264.205549464009,1264.205549464009,1264.205549464009,1248.8118542250545,1214.8862762522185,1202.2937858399318,1202.2937858399318,1226.5116597492577,1226.5116597492577,1241.0245410442703,1243.5792626285022,1243.5792626285022,1243.5792626285022,1243.5792626285022,1243.5792626285022,1243.5792626285022,1243.5792626285022,1243.5792626285022,1223.7078477355853,1223.7078477355853,1204.0178520558131,1210.4473765113041,1210.4473765113041,1213.8654021610203,1213.8654021610203,1213.8654021610203,1213.8654021610203,1194.1494184445107,1210.027005677834,1210.027005677834,1213.2218685373343,1213.2218685373343,1195.0209184544399,1195.0209184544399,1195.0209184544399,1195.0209184544399,1195.0209184544399,1195.0209184544399,1191.2991982296803,1232.8650487367947,1232.8650487367947,1205.223334396975,1207.4492154194807,1251.2653738298823,1251.2653738298823,1239.285284030056,1239.285284030056,1236.0084119625483,1236.0084119625483,1236.0084119625483,1236.9462058383594,1270.7713611043216,1270.7713611043216,1270.7713611043216,1284.0331530057788,1286.428180054912,1309.9722905797034,1309.9722905797034,1309.9722905797034,1317.0053712033434,1280.4229970157917,1280.4229970157917,1282.797189385037,1282.797189385037,1282.797189385037,1264.7545655410747,1264.7545655410747,1264.7545655410747,1251.8815282461962,1251.8815282461962,1253.8813486931335,1260.7991463891635,1260.7991463891635,1260.7991463891635,1305.5249023552271,1305.5249023552271,1305.5249023552271,1299.3626297441504,1272.5828263603196,1298.1557545580392,1291.582578617899,1291.582578617899,1291.582578617899,1291.582578617899,1291.582578617899,1291.582578617899,1291.582578617899,1275.8892624097145,1255.2359498926826,1279.1963526298912,1301.1824784344121,1301.1824784344121,1314.2274187076946,1314.2274187076946,1340.4162139350194,1324.1661299704958,1297.666162824895,1297.666162824895]},{"name":"ID","datatype":"Int64","bit_settings":"","values":[207,207,207,207,207,207,207,207,207,207,207,207,207,207,207,207,207,207,207,207,207,207,207,207,207,207,207,207,207,207,207,207,207,207,207,207,207,207,207,207,207,207,207,207,207,207,207,207,207,207,207,207,207,207,207,207,207,207,207,207,207,207,207,207,207,207,207,207,207,207,207,207,207,207,207,207,207,207,207,207,207,207,207,207,207,207,207,207,207,207,207,207,207,207,207,207,207,207,207,207,207,207,207,207,207,207,207,207,207,207,207]}]}